s3fit/__init__.py
s3fit/auxiliary_func.py
s3fit/config_frame.py
s3fit/extinct_law.py
s3fit/fit_frame.py
s3fit/phot_frame.py
s3fit/model_frames/__init__.py
s3fit/model_frames/agn_frame.py
s3fit/model_frames/line_frame.py
s3fit/model_frames/stellar_frame.py
s3fit/model_frames/torus_frame.py
s3fit-2.2.5.dist-info/licenses/LICENSE
s3fit-2.2.5.dist-info/METADATA
s3fit-2.2.5.dist-info/WHEEL
s3fit-2.2.5.dist-info/top_level.txt
s3fit-2.2.5.dist-info/RECORD
