Metadata-Version: 2.4
Name: s3fit
Version: 2.2.5
Summary: S3Fit: a Simultaneous Spectrum and photometric-SED Fitting code for observation of galaxies
Author-email: Xiaoyang Chen <s3fit@xychen.me>
License-Expression: GPL-3.0-or-later
Project-URL: Homepage, https://github.com/xychcz
Project-URL: Repository, https://github.com/xychcz/S3Fit
Project-URL: Documentation, https://github.com/xychcz/S3Fit/tree/main/manuals
Project-URL: Changelog, https://github.com/xychcz/S3Fit/releases
Keywords: spectral fitting,SED fitting,galaxy,astronomy
Classifier: Development Status :: 5 - Production/Stable
Classifier: Topic :: Scientific/Engineering :: Astronomy
Classifier: Programming Language :: Python :: 3.10
Requires-Python: >=3.10
License-File: LICENSE
Requires-Dist: scipy>=1.12.0
Requires-Dist: numpy>=1.26.4
Requires-Dist: astropy>=6.0.0
Requires-Dist: joblib>=1.5.2
Requires-Dist: matplotlib>=3.9.1
Provides-Extra: pyneb
Requires-Dist: pyneb>=1.1.23; extra == "pyneb"
Dynamic: license-file
